MANIFEST.in
README.md
setup.py
althea/__init__.py
althea/bin.py
althea/registrator.py
althea/server.py
althea.egg-info/PKG-INFO
althea.egg-info/SOURCES.txt
althea.egg-info/dependency_links.txt
althea.egg-info/entry_points.txt
althea.egg-info/not-zip-safe
althea.egg-info/requires.txt
althea.egg-info/top_level.txt
althea/__pycache__/__init__.cpython-35.pyc
althea/dynamicloader/__init__.py
althea/dynamicloader/dynamicloader.py
althea/dynamicloader/__pycache__/__init__.cpython-35.pyc
althea/dynamicloader/__pycache__/dynamicloader.cpython-35.pyc
althea/model_db/framingham30yr/model.p
althea/model_db/framingham30yr/save_model_pickle.py
althea/model_db/framingham30yr/score.py
althea/model_db/murdockdthModel/model.p
althea/model_db/murdockdthModel/save_model_pickle.py
althea/model_db/murdockdthModel/score.py
althea/model_db/pooledCohorts/score.py
althea/resources/__init__.py
althea/resources/base.py
althea/resources/__pycache__/__init__.cpython-35.pyc
althea/resources/__pycache__/base.cpython-35.pyc
althea/static/add_button.js
althea/templates/index.html
althea/templates/layout.html
althea/templates/macros.html
althea/templates/models.html
althea/templates/register.html
althea/templates/root.html
althea/templates/template.html