Metadata-Version: 1.0
Name: althea
Version: 0.0.2
Summary: ALgoriTHms Exposed through a RESTful API .
Home-page: https://github.com/benneely/althea
Author: Ben Neely
Author-email: nigelneely@gmail.com
License: GNU3
Platform: UNKNOWN
